pid_file_checker/__init__.py
pid_file_checker/checker.py
pid_file_checker/exceptions.py
pid_file_checker-1.0.1.dist-info/entry_points.txt
pid_file_checker-1.0.1.dist-info/WHEEL
pid_file_checker-1.0.1.dist-info/METADATA
pid_file_checker-1.0.1.dist-info/RECORD
