Metadata-Version: 2.1
Name: pid-file-checker
Version: 1.0.1
Summary: Monitor a pid file
Home-page: https://github.com/itsolutionsfactory/pid-file-checker
License: MIT
Keywords: pid,daemon,monitoring
Author: Gabriel Augendre
Author-email: gabriel.augendre@itsfactory.fr
Maintainer: Gabriel Augendre
Maintainer-email: gabriel.augendre@itsfactory.fr
Requires-Python: >=3.7
Classifier: Development Status :: 5 - Production/Stable
Classifier: Environment :: Console
Classifier: Intended Audience :: System Administrators
Classifier: License :: OSI Approved :: MIT License
Classifier: Operating System :: MacOS
Classifier: Operating System :: Unix
Classifier: Programming Language :: Python :: 3
Classifier: Programming Language :: Python :: 3.7
Classifier: Programming Language :: Python :: 3.8
Classifier: Programming Language :: Python :: 3.9
Classifier: Topic :: System :: Systems Administration
Classifier: Topic :: Utilities
Requires-Dist: psutil (>=5.8.0)
Project-URL: Repository, https://github.com/itsolutionsfactory/pid-file-checker
